{"cameraMode":{"drawMode":0,"name":"Shaded","section":"Shading Mode"},"sceneLighting":true,"audioPlay":false,"sceneViewState":{"m_AlwaysRefresh":false,"showFog":true,"showSkybox":true,"showFlares":true,"showImageEffects":true,"showParticleSystems":true,"showVisualEffectGraphs":true,"m_FxEnabled":true},"in2DMode":false,"pivot":{"x":-0.6669601798057556,"y":-9.810373306274414,"z":-26.633718490600587},"rotation":{"x":-0.008546476252377034,"y":0.9702807068824768,"z":-0.23930589854717256,"w":-0.03465268015861511},"size":28.35492706298828,"orthographic":false}